[
  {"date":"2026-02-14","sleepHours":7.6,"moodScore":6.8,"stressScore":2.8,"cravingScore":0.8,"energyScore":6.4,"steps":7600,"restingHeartRate":65},
  {"date":"2026-02-15","sleepHours":7.4,"moodScore":6.7,"stressScore":3.0,"cravingScore":0.9,"energyScore":6.3,"steps":7420,"restingHeartRate":65},
  {"date":"2026-02-16","sleepHours":7.7,"moodScore":6.9,"stressScore":2.9,"cravingScore":0.8,"energyScore":6.6,"steps":7810,"restingHeartRate":64},
  {"date":"2026-02-17","sleepHours":7.5,"moodScore":6.6,"stressScore":3.1,"cravingScore":1.0,"energyScore":6.2,"steps":7260,"restingHeartRate":66},
  {"date":"2026-02-18","sleepHours":7.3,"moodScore":6.5,"stressScore":3.2,"cravingScore":1.0,"energyScore":6.1,"steps":7010,"restingHeartRate":66},
  {"date":"2026-02-19","sleepHours":7.2,"moodScore":6.4,"stressScore":3.3,"cravingScore":1.1,"energyScore":6.0,"steps":6930,"restingHeartRate":67},
  {"date":"2026-02-20","sleepHours":7.1,"moodScore":6.4,"stressScore":3.3,"cravingScore":1.1,"energyScore":5.9,"steps":6820,"restingHeartRate":67},
  {"date":"2026-02-21","sleepHours":7.0,"moodScore":6.3,"stressScore":3.5,"cravingScore":1.2,"energyScore":5.8,"steps":6710,"restingHeartRate":68},
  {"date":"2026-02-22","sleepHours":6.8,"moodScore":6.1,"stressScore":3.8,"cravingScore":1.4,"energyScore":5.6,"steps":6500,"restingHeartRate":69},
  {"date":"2026-02-23","sleepHours":6.7,"moodScore":6.0,"stressScore":4.0,"cravingScore":1.5,"energyScore":5.5,"steps":6420,"restingHeartRate":69},
  {"date":"2026-02-24","sleepHours":6.5,"moodScore":5.8,"stressScore":4.2,"cravingScore":1.7,"energyScore":5.2,"steps":6200,"restingHeartRate":70},
  {"date":"2026-02-25","sleepHours":6.4,"moodScore":5.8,"stressScore":4.3,"cravingScore":1.8,"energyScore":5.1,"steps":6110,"restingHeartRate":70},
  {"date":"2026-02-26","sleepHours":6.2,"moodScore":5.7,"stressScore":4.6,"cravingScore":2.0,"energyScore":4.9,"steps":5980,"restingHeartRate":71},
  {"date":"2026-02-27","sleepHours":6.0,"moodScore":5.5,"stressScore":4.9,"cravingScore":2.2,"energyScore":4.6,"steps":5850,"restingHeartRate":72},
  {"date":"2026-02-28","sleepHours":5.9,"moodScore":5.4,"stressScore":5.1,"cravingScore":2.4,"energyScore":4.4,"steps":5730,"restingHeartRate":72},
  {"date":"2026-03-01","sleepHours":6.1,"moodScore":5.6,"stressScore":4.8,"cravingScore":2.2,"energyScore":4.8,"steps":5900,"restingHeartRate":71},
  {"date":"2026-03-02","sleepHours":6.0,"moodScore":5.5,"stressScore":5.0,"cravingScore":2.3,"energyScore":4.7,"steps":5780,"restingHeartRate":72},
  {"date":"2026-03-03","sleepHours":5.8,"moodScore":5.3,"stressScore":5.2,"cravingScore":2.5,"energyScore":4.5,"steps":5600,"restingHeartRate":73},
  {"date":"2026-03-04","sleepHours":5.7,"moodScore":5.2,"stressScore":5.4,"cravingScore":2.6,"energyScore":4.3,"steps":5480,"restingHeartRate":73},
  {"date":"2026-03-05","sleepHours":5.6,"moodScore":5.0,"stressScore":5.7,"cravingScore":2.9,"energyScore":4.1,"steps":5340,"restingHeartRate":74},
  {"date":"2026-03-06","sleepHours":5.4,"moodScore":4.8,"stressScore":6.0,"cravingScore":3.2,"energyScore":3.9,"steps":5200,"restingHeartRate":75},
  {"date":"2026-03-07","sleepHours":5.2,"moodScore":4.6,"stressScore":6.4,"cravingScore":3.6,"energyScore":3.6,"steps":5020,"restingHeartRate":76},
  {"date":"2026-03-08","sleepHours":5.1,"moodScore":4.5,"stressScore":6.6,"cravingScore":3.8,"energyScore":3.5,"steps":4980,"restingHeartRate":76},
  {"date":"2026-03-09","sleepHours":5.0,"moodScore":4.4,"stressScore":6.7,"cravingScore":4.1,"energyScore":3.4,"steps":4920,"restingHeartRate":77},
  {"date":"2026-03-10","sleepHours":4.9,"moodScore":4.2,"stressScore":7.0,"cravingScore":4.4,"energyScore":3.2,"steps":4800,"restingHeartRate":78},
  {"date":"2026-03-11","sleepHours":4.8,"moodScore":4.1,"stressScore":7.2,"cravingScore":4.6,"energyScore":3.1,"steps":4720,"restingHeartRate":79},
  {"date":"2026-03-12","sleepHours":5.3,"moodScore":4.5,"stressScore":6.5,"cravingScore":4.0,"energyScore":3.8,"steps":5160,"restingHeartRate":76},
  {"date":"2026-03-13","sleepHours":5.7,"moodScore":4.9,"stressScore":6.1,"cravingScore":3.5,"energyScore":4.2,"steps":5520,"restingHeartRate":74},
  {"date":"2026-03-14","sleepHours":6.0,"moodScore":5.2,"stressScore":5.8,"cravingScore":3.1,"energyScore":4.6,"steps":5890,"restingHeartRate":73},
  {"date":"2026-03-15","sleepHours":6.2,"moodScore":5.4,"stressScore":5.4,"cravingScore":2.8,"energyScore":4.9,"steps":6120,"restingHeartRate":72}
]
